Mangandi/__init__.py
Mangandi/audio.py
Mangandi/just.py
Mangandi/mangandipro.py
Mangandi/upload.py
Mangandi/video.py
mangandi-1.0.14.dist-info/licenses/LICENSE
mangandi-1.0.14.dist-info/METADATA
mangandi-1.0.14.dist-info/WHEEL
mangandi-1.0.14.dist-info/top_level.txt
mangandi-1.0.14.dist-info/RECORD
